odoo/addons/connector_acp/README.rst
odoo/addons/connector_acp/__init__.py
odoo/addons/connector_acp/__manifest__.py
odoo/addons/connector_acp/i18n/connector_acp.pot
odoo/addons/connector_acp/i18n/es.po
odoo/addons/connector_acp/i18n/es_CL.po
odoo/addons/connector_acp/models/__init__.py
odoo/addons/connector_acp/models/backend_acp.py
odoo/addons/connector_acp/models/etd_certificate.py
odoo/addons/connector_acp/models/etd_document.py
odoo/addons/connector_acp/models/etd_document_file.py
odoo/addons/connector_acp/models/etd_mixin.py
odoo/addons/connector_acp/models/etd_signature.py
odoo/addons/connector_acp/models/res_company.py
odoo/addons/connector_acp/models/res_country.py
odoo/addons/connector_acp/readme/CONFIGURE.rst
odoo/addons/connector_acp/readme/CONTRIBUTORS.rst
odoo/addons/connector_acp/readme/DESCRIPTION.rst
odoo/addons/connector_acp/readme/ROADMAP.rst
odoo/addons/connector_acp/readme/USAGE.rst
odoo/addons/connector_acp/security/ir.model.access.csv
odoo/addons/connector_acp/static/description/icon.png
odoo/addons/connector_acp/static/description/index.html
odoo/addons/connector_acp/views/backend_acp.xml
odoo/addons/connector_acp/views/etd_certificate.xml
odoo/addons/connector_acp/views/etd_document_file.xml
odoo/addons/connector_acp/views/etd_signature.xml
odoo/addons/connector_acp/views/res_company.xml
odoo/addons/connector_acp/views/res_country.xml
odoo12_addon_connector_acp-12.0.3.0.2.dist-info/METADATA
odoo12_addon_connector_acp-12.0.3.0.2.dist-info/WHEEL
odoo12_addon_connector_acp-12.0.3.0.2.dist-info/top_level.txt
odoo12_addon_connector_acp-12.0.3.0.2.dist-info/RECORD
