Metadata-Version: 2.1
Name: odoo12-addon-connector-acp
Version: 12.0.3.0.2
Summary: Get your documents signed by an Authorized Certification Provider
Home-page: https://github.com/OCA/l10n-chile
Author: Daniel Santibáñez Polanco, Cooperativa OdooCoop, Konos, Open Source Integrators, Odoo Community Association (OCA)
Author-email: support@odoo-community.org
License: AGPL-3
Platform: UNKNOWN
Classifier: Programming Language :: Python
Classifier: Framework :: Odoo
Classifier: License :: OSI Approved :: GNU Affero General Public License v3
Classifier: Development Status :: 4 - Beta
Requires-Python: >=3.5
Requires-Dist: collections
Requires-Dist: jinja2
Requires-Dist: lxml
Requires-Dist: odoo12-addon-connector
Requires-Dist: odoo (<12.1dev,>=12.0a)
